Authentication/__init__.py
Authentication/config/logging_config.py
Authentication/config/spciq-api-authentication-application.properties
Authentication/constants/caching_constants.py
Authentication/constants/config_constants.py
Authentication/constants/token_constants.py
Authentication/exception/authenticate_exception.py
Authentication/model/sdk_proxy.py
Authentication/model/token_response.py
Authentication/services/sdk_authenticate_service.py
Authentication/services/impl/sdk_authenticate_service_impl.py
Authentication/services/support/rest_gateway_support.py
Authentication/util/property_util.py
tests/auth_module_tests.py
tests/auth_negative_tests.py
tests/get_refresh_token_tests.py
tests/get_token_test.py
authtestdistribution-1.0.2.dist-info/METADATA
authtestdistribution-1.0.2.dist-info/WHEEL
authtestdistribution-1.0.2.dist-info/top_level.txt
authtestdistribution-1.0.2.dist-info/RECORD
