Metadata-Version: 2.1
Name: authtestdistribution
Version: 1.0.2
Summary: Module for authentication pkg distribution test
Author-email: sp <sp@email.com>
Classifier: Programming Language :: Python :: 3
Classifier: License :: OSI Approved :: MIT License
Classifier: Operating System :: OS Independent
Requires-Dist: requests
